flounder/__init__.py
flounder/flounder.py
mermaid_flounder-1.0.0b1.dist-info/METADATA
mermaid_flounder-1.0.0b1.dist-info/WHEEL
mermaid_flounder-1.0.0b1.dist-info/top_level.txt
mermaid_flounder-1.0.0b1.dist-info/RECORD
