Metadata-Version: 2.1
Name: mermaid-flounder
Version: 1.0.0b1
Summary: Automation tools for Mermaid diagram
Home-page: https://github.com/ForestHouse2316/flounder
Author: ForestHouse
Author-email: foresthouse2316@gmail.com
License: MIT
Platform: UNKNOWN
Requires-Python: >=3
